flatten_json/__init__.py
ccl_flatten_json-0.2.2.dist-info/LICENSE
ccl_flatten_json-0.2.2.dist-info/METADATA
ccl_flatten_json-0.2.2.dist-info/WHEEL
ccl_flatten_json-0.2.2.dist-info/entry_points.txt
ccl_flatten_json-0.2.2.dist-info/top_level.txt
ccl_flatten_json-0.2.2.dist-info/RECORD
