Metadata-Version: 2.1
Name: ccl-flatten-json
Version: 0.2.2
Summary: Flatten JSON objects
Home-page: https://github.com/cchangelabs/ccl-flatten-json
Author: C-Change Labs Inc.
Author-email: support@c-change-labs.com
License: MIT
Keywords: json,flatten,pandas
License-File: LICENSE
Requires-Dist: six
